RDSTools/RDSToolsToyData.csv
RDSTools/__init__.py
RDSTools/bootstrap.py
RDSTools/data_processing.py
RDSTools/load_data.py
RDSTools/mean.py
RDSTools/network_graph.py
RDSTools/parallel_bootstrap.py
RDSTools/rds_map.py
RDSTools/regression.py
RDSTools/table.py
rdstools-0.1.3.dist-info/licenses/LICENSE
rdstools-0.1.3.dist-info/METADATA
rdstools-0.1.3.dist-info/WHEEL
rdstools-0.1.3.dist-info/top_level.txt
rdstools-0.1.3.dist-info/RECORD
