Metadata-Version: 2.4
Name: RDSTools
Version: 0.1.3
Summary: Python tools for Respondent-Driven Sampling (RDS) analysis
Author-email: Jay Kim <jayhk@umich.edu>, Jay Kim <aquilanima96@gmail.com>
License: MIT
Project-URL: Repository, https://github.com/RDSTools/RDSTools-Python-Package
Project-URL: Documentation, https://rdstools-python-package.readthedocs.io/en/latest/
Keywords: RDS,respondent-driven sampling,sampling,statistics,survey,epidemiology
Classifier: Development Status :: 3 - Alpha
Classifier: Intended Audience :: Science/Research
Classifier: License :: OSI Approved :: MIT License
Classifier: Programming Language :: Python :: 3
Classifier: Programming Language :: Python :: 3.8
Classifier: Programming Language :: Python :: 3.9
Classifier: Programming Language :: Python :: 3.10
Classifier: Programming Language :: Python :: 3.11
Classifier: Programming Language :: Python :: 3.12
Classifier: Topic :: Scientific/Engineering :: Information Analysis
Classifier: Operating System :: OS Independent
Requires-Python: >=3.8
License-File: LICENSE
Requires-Dist: pandas>=1.3.0
Requires-Dist: numpy>=1.20.0
Requires-Dist: statsmodels>=0.12.0
Requires-Dist: scipy>=1.7.0
Requires-Dist: patsy>=0.5.0
Requires-Dist: folium>=0.12.0
Requires-Dist: matplotlib>=3.3.0
Requires-Dist: networkx>=2.5
Requires-Dist: python-igraph>=0.9.0
Provides-Extra: dev
Requires-Dist: pytest>=6.0; extra == "dev"
Requires-Dist: pytest-cov>=3.0; extra == "dev"
Requires-Dist: black>=22.0; extra == "dev"
Requires-Dist: flake8>=4.0; extra == "dev"
Provides-Extra: viz
Requires-Dist: pygraphviz>=1.7; extra == "viz"
Dynamic: license-file
